building_blocks/__init__.py
building_blocks/application/README.md
building_blocks/application/__init__.py
building_blocks/application/ports/__init__.py
building_blocks/application/ports/inbound/__init__.py
building_blocks/application/ports/inbound/message_handler.py
building_blocks/application/ports/inbound/use_case.py
building_blocks/application/ports/outbound/__init__.py
building_blocks/application/ports/outbound/command_sender.py
building_blocks/application/ports/outbound/event_publisher.py
building_blocks/application/ports/outbound/message_bus.py
building_blocks/application/ports/outbound/notifier.py
building_blocks/application/ports/outbound/query_fetcher.py
building_blocks/application/ports/outbound/repository.py
building_blocks/application/ports/outbound/unit_of_work.py
building_blocks/domain/README.md
building_blocks/domain/__init__.py
building_blocks/domain/aggregate_root.py
building_blocks/domain/entity.py
building_blocks/domain/errors/__init__.py
building_blocks/domain/errors/draft_entity_is_not_hashable_error.py
building_blocks/domain/errors/entity_id_none_error.py
building_blocks/domain/messages/__init__.py
building_blocks/domain/messages/command.py
building_blocks/domain/messages/event.py
building_blocks/domain/messages/message.py
building_blocks/domain/messages/query.py
building_blocks/domain/value_object.py
building_blocks/foundation/__init__.py
building_blocks/foundation/debuggable.py
building_blocks/foundation/errors/__init__.py
building_blocks/foundation/errors/base.py
building_blocks/foundation/errors/cant_modify_immutable_attribute_error.py
building_blocks/foundation/errors/core.py
building_blocks/foundation/errors/rule_violation_error.py
building_blocks/foundation/errors/validation_error.py
building_blocks/foundation/mapper.py
building_blocks/foundation/meta/__init__.py
building_blocks/foundation/meta/final_meta.py
building_blocks/foundation/ports.py
building_blocks/foundation/result.py
building_blocks/foundation/result_mapper.py
building_blocks_toolkit-0.3.5.dist-info/LICENSE
building_blocks_toolkit-0.3.5.dist-info/METADATA
building_blocks_toolkit-0.3.5.dist-info/WHEEL
building_blocks_toolkit-0.3.5.dist-info/RECORD
