Metadata-Version: 2.1
Name: building-blocks-toolkit
Version: 0.3.5
Summary: Composable toolkit for clean, testable, and maintainable Python applications
Home-page: https://building-blocks-org.github.io/building-blocks/
License: MIT
Keywords: python library,clean architecture,hexagonal architecture,domain-driven design,ddd,framework-agnostic,software architecture,software design,software engineering,ports and adapters,adapter pattern,application service,repository pattern,message bus,notifier pattern,data mapper,result pattern,result monad,ok,err,either type,debuggable,use case,domain layer,application layer,presentation layer,foundation,building blocks
Author: BuildingBlocks Org
Author-email: buildingblocksorganization91@gmail.com
Requires-Python: >=3.12,<4.0
Classifier: License :: OSI Approved :: MIT License
Classifier: Programming Language :: Python :: 3
Classifier: Programming Language :: Python :: 3.12
Project-URL: Repository, https://github.com/building-blocks-org/building-blocks
